[{"eventId":80239,"type":1,"targetId":94035007,"value":0,"priority":1,"overwriteEquipIconId":141,"overwriteIconId":142,"script":{"handle":"0x6fbc9734e0"},"scriptXuyaoshiyongjsonchulidebianliang":"null"},{"eventId":80239,"type":1,"targetId":94035009,"value":0,"priority":2,"overwriteEquipIconId":141,"overwriteIconId":142,"script":{"handle":"0x6fbc973360"},"scriptXuyaoshiyongjsonchulidebianliang":"null"},{"eventId":80239,"type":1,"targetId":94035010,"value":0,"priority":3,"overwriteEquipIconId":141,"overwriteIconId":142,"script":{"handle":"0x6fbc9731e0"},"scriptXuyaoshiyongjsonchulidebianliang":"null"},{"eventId":80239,"type":1,"targetId":94035015,"value":0,"priority":6,"overwriteEquipIconId":141,"overwriteIconId":142,"script":{"handle":"0x6fbc973060"},"scriptXuyaoshiyongjsonchulidebianliang":"null"},{"eventId":80239,"type":1,"targetId":94035020,"value":0,"priority":9,"overwriteEquipIconId":141,"overwriteIconId":142,"script":{"handle":"0x6fbcc22ea0"},"scriptXuyaoshiyongjsonchulidebianliang":"null"},{"eventId":80239,"type":1,"targetId":94035021,"value":0,"priority":7,"overwriteEquipIconId":141,"overwriteIconId":142,"script":{"handle":"0x6fbcc22d20"},"scriptXuyaoshiyongjsonchulidebianliang":"null"},{"eventId":80239,"type":1,"targetId":94035025,"value":0,"priority":12,"overwriteEquipIconId":141,"overwriteIconId":142,"script":{"handle":"0x6fbcc22ba0"},"scriptXuyaoshiyongjsonchulidebianliang":"null"},{"eventId":80239,"type":1,"targetId":94035026,"value":0,"priority":10,"overwriteEquipIconId":141,"overwriteIconId":142,"script":{"handle":"0x6fbcc22a20"},"scriptXuyaoshiyongjsonchulidebianliang":"null"},{"eventId":80239,"type":1,"targetId":94035031,"value":0,"priority":13,"overwriteEquipIconId":141,"overwriteIconId":142,"script":{"handle":"0x6fbcc228a0"},"scriptXuyaoshiyongjsonchulidebianliang":"null"},{"eventId":80239,"type":1,"targetId":94035034,"value":0,"priority":14,"overwriteEquipIconId":141,"overwriteIconId":142,"script":{"handle":"0x6fbcc22720"},"scriptXuyaoshiyongjsonchulidebianliang":"null"},{"eventId":80239,"type":1,"targetId":94035036,"value":0,"priority":15,"overwriteEquipIconId":141,"overwriteIconId":142,"script":{"handle":"0x6fbcc225a0"},"scriptXuyaoshiyongjsonchulidebianliang":"null"},{"eventId":80239,"type":1,"targetId":94035075,"value":0,"priority":5,"overwriteEquipIconId":141,"overwriteIconId":142,"script":{"handle":"0x6fbcc22420"},"scriptXuyaoshiyongjsonchulidebianliang":"null"},{"eventId":80239,"type":1,"targetId":94035076,"value":0,"priority":4,"overwriteEquipIconId":141,"overwriteIconId":142,"script":{"handle":"0x6fbcc222a0"},"scriptXuyaoshiyongjsonchulidebianliang":"null"},{"eventId":80239,"type":1,"targetId":94035077,"value":0,"priority":8,"overwriteEquipIconId":141,"overwriteIconId":142,"script":{"handle":"0x6fbcc22120"},"scriptXuyaoshiyongjsonchulidebianliang":"null"},{"eventId":80239,"type":1,"targetId":94035078,"value":0,"priority":11,"overwriteEquipIconId":141,"overwriteIconId":142,"script":{"handle":"0x6fbcc2af60"},"scriptXuyaoshiyongjsonchulidebianliang":"null"},{"eventId":80290,"type":1,"targetId":94049507,"value":0,"priority":1,"overwriteEquipIconId":141,"overwriteIconId":142,"script":{"handle":"0x6fbcc2ade0"},"scriptXuyaoshiyongjsonchulidebianliang":"null"},{"eventId":80290,"type":1,"targetId":94049509,"value":0,"priority":2,"overwriteEquipIconId":141,"overwriteIconId":142,"script":{"handle":"0x6fbcc2ac60"},"scriptXuyaoshiyongjsonchulidebianliang":"null"},{"eventId":80290,"type":1,"targetId":94049510,"value":0,"priority":3,"overwriteEquipIconId":141,"overwriteIconId":142,"script":{"handle":"0x6fbcc2aae0"},"scriptXuyaoshiyongjsonchulidebianliang":"null"},{"eventId":80290,"type":1,"targetId":94049515,"value":0,"priority":6,"overwriteEquipIconId":141,"overwriteIconId":142,"script":{"handle":"0x6fbcc2a960"},"scriptXuyaoshiyongjsonchulidebianliang":"null"},{"eventId":80290,"type":1,"targetId":94049520,"value":0,"priority":9,"overwriteEquipIconId":141,"overwriteIconId":142,"script":{"handle":"0x6fbcc2a7e0"},"scriptXuyaoshiyongjsonchulidebianliang":"null"},{"eventId":80290,"type":1,"targetId":94049521,"value":0,"priority":7,"overwriteEquipIconId":141,"overwriteIconId":142,"script":{"handle":"0x6fbcc2a660"},"scriptXuyaoshiyongjsonchulidebianliang":"null"},{"eventId":80290,"type":1,"targetId":94049525,"value":0,"priority":12,"overwriteEquipIconId":141,"overwriteIconId":142,"script":{"handle":"0x6fbcc2a4e0"},"scriptXuyaoshiyongjsonchulidebianliang":"null"},{"eventId":80290,"type":1,"targetId":94049526,"value":0,"priority":10,"overwriteEquipIconId":141,"overwriteIconId":142,"script":{"handle":"0x6fbcc2a360"},"scriptXuyaoshiyongjsonchulidebianliang":"null"},{"eventId":80290,"type":1,"targetId":94049531,"value":0,"priority":13,"overwriteEquipIconId":141,"overwriteIconId":142,"script":{"handle":"0x6fbcc2a1e0"},"scriptXuyaoshiyongjsonchulidebianliang":"null"},{"eventId":80290,"type":1,"targetId":94049534,"value":0,"priority":14,"overwriteEquipIconId":141,"overwriteIconId":142,"script":{"handle":"0x6fbcc2a060"},"scriptXuyaoshiyongjsonchulidebianliang":"null"},{"eventId":80290,"type":1,"targetId":94049536,"value":0,"priority":15,"overwriteEquipIconId":141,"overwriteIconId":142,"script":{"handle":"0x6fbcc30ea0"},"scriptXuyaoshiyongjsonchulidebianliang":"null"},{"eventId":80290,"type":1,"targetId":94049575,"value":0,"priority":5,"overwriteEquipIconId":141,"overwriteIconId":142,"script":{"handle":"0x6fbcc30d20"},"scriptXuyaoshiyongjsonchulidebianliang":"null"},{"eventId":80290,"type":1,"targetId":94049576,"value":0,"priority":4,"overwriteEquipIconId":141,"overwriteIconId":142,"script":{"handle":"0x6fbcc30ba0"},"scriptXuyaoshiyongjsonchulidebianliang":"null"},{"eventId":80290,"type":1,"targetId":94049577,"value":0,"priority":8,"overwriteEquipIconId":141,"overwriteIconId":142,"script":{"handle":"0x6fbcc30a20"},"scriptXuyaoshiyongjsonchulidebianliang":"null"},{"eventId":80290,"type":1,"targetId":94049578,"value":0,"priority":11,"overwriteEquipIconId":141,"overwriteIconId":142,"script":{"handle":"0x6fbcc308a0"},"scriptXuyaoshiyongjsonchulidebianliang":"null"},{"eventId":80379,"type":1,"targetId":94071907,"value":0,"priority":1,"overwriteEquipIconId":141,"overwriteIconId":142,"script":{"handle":"0x6fbcc30720"},"scriptXuyaoshiyongjsonchulidebianliang":"null"},{"eventId":80379,"type":1,"targetId":94071909,"value":0,"priority":2,"overwriteEquipIconId":141,"overwriteIconId":142,"script":{"handle":"0x6fbcc305a0"},"scriptXuyaoshiyongjsonchulidebianliang":"null"},{"eventId":80379,"type":1,"targetId":94071910,"value":0,"priority":3,"overwriteEquipIconId":141,"overwriteIconId":142,"script":{"handle":"0x6fbcc30420"},"scriptXuyaoshiyongjsonchulidebianliang":"null"},{"eventId":80379,"type":1,"targetId":94071915,"value":0,"priority":6,"overwriteEquipIconId":141,"overwriteIconId":142,"script":{"handle":"0x6fbcc302a0"},"scriptXuyaoshiyongjsonchulidebianliang":"null"},{"eventId":80379,"type":1,"targetId":94071920,"value":0,"priority":9,"overwriteEquipIconId":141,"overwriteIconId":142,"script":{"handle":"0x6fbcc30120"},"scriptXuyaoshiyongjsonchulidebianliang":"null"},{"eventId":80379,"type":1,"targetId":94071921,"value":0,"priority":7,"overwriteEquipIconId":141,"overwriteIconId":142,"script":{"handle":"0x6fbcc38f60"},"scriptXuyaoshiyongjsonchulidebianliang":"null"},{"eventId":80379,"type":1,"targetId":94071925,"value":0,"priority":12,"overwriteEquipIconId":141,"overwriteIconId":142,"script":{"handle":"0x6fbcc38de0"},"scriptXuyaoshiyongjsonchulidebianliang":"null"},{"eventId":80379,"type":1,"targetId":94071926,"value":0,"priority":10,"overwriteEquipIconId":141,"overwriteIconId":142,"script":{"handle":"0x6fbcc38c60"},"scriptXuyaoshiyongjsonchulidebianliang":"null"},{"eventId":80379,"type":1,"targetId":94071931,"value":0,"priority":13,"overwriteEquipIconId":141,"overwriteIconId":142,"script":{"handle":"0x6fbcc38ae0"},"scriptXuyaoshiyongjsonchulidebianliang":"null"},{"eventId":80379,"type":1,"targetId":94071934,"value":0,"priority":14,"overwriteEquipIconId":141,"overwriteIconId":142,"script":{"handle":"0x6fbcc38960"},"scriptXuyaoshiyongjsonchulidebianliang":"null"},{"eventId":80379,"type":1,"targetId":94071936,"value":0,"priority":15,"overwriteEquipIconId":141,"overwriteIconId":142,"script":{"handle":"0x6fbcc387e0"},"scriptXuyaoshiyongjsonchulidebianliang":"null"},{"eventId":80379,"type":1,"targetId":94071975,"value":0,"priority":5,"overwriteEquipIconId":141,"overwriteIconId":142,"script":{"handle":"0x6fbcc38660"},"scriptXuyaoshiyongjsonchulidebianliang":"null"},{"eventId":80379,"type":1,"targetId":94071976,"value":0,"priority":4,"overwriteEquipIconId":141,"overwriteIconId":142,"script":{"handle":"0x6fbcc384e0"},"scriptXuyaoshiyongjsonchulidebianliang":"null"},{"eventId":80379,"type":1,"targetId":94071977,"value":0,"priority":8,"overwriteEquipIconId":141,"overwriteIconId":142,"script":{"handle":"0x6fbcc38360"},"scriptXuyaoshiyongjsonchulidebianliang":"null"},{"eventId":80379,"type":1,"targetId":94071978,"value":0,"priority":11,"overwriteEquipIconId":141,"overwriteIconId":142,"script":{"handle":"0x6fbcc381e0"},"scriptXuyaoshiyongjsonchulidebianliang":"null"}]