[{"stageId":94071401,"sceneType":1,"idx":1,"scriptIds":["9407145010"],"playProbabirity":1000,"playCondType":0,"playCondValues":[]},{"stageId":94071401,"sceneType":4,"idx":1,"scriptIds":["9407145110"],"playProbabirity":1000,"playCondType":0,"playCondValues":[]},{"stageId":94071401,"sceneType":6,"idx":1,"scriptIds":["9407145210"],"playProbabirity":1000,"playCondType":0,"playCondValues":[]},{"stageId":94071401,"sceneType":6,"idx":2,"scriptIds":["9407145220"],"playProbabirity":1000,"playCondType":0,"playCondValues":[]},{"stageId":94071401,"sceneType":6,"idx":3,"scriptIds":["9407145230"],"playProbabirity":1000,"playCondType":0,"playCondValues":[]},{"stageId":94071401,"sceneType":8,"idx":1,"scriptIds":["9407145310"],"playProbabirity":1000,"playCondType":0,"playCondValues":[]},{"stageId":94071401,"sceneType":9,"idx":1,"scriptIds":["9407145410"],"playProbabirity":1000,"playCondType":5,"playCondValues":["3"]},{"stageId":94071401,"sceneType":9,"idx":2,"scriptIds":["9407145420"],"playProbabirity":1000,"playCondType":5,"playCondValues":["3"]},{"stageId":94071401,"sceneType":9,"idx":3,"scriptIds":["9407145430"],"playProbabirity":1000,"playCondType":5,"playCondValues":["3"]},{"stageId":94071401,"sceneType":11,"idx":1,"scriptIds":["9407145510"],"playProbabirity":1000,"playCondType":1,"playCondValues":["1"]},{"stageId":94071401,"sceneType":12,"idx":1,"scriptIds":["9407145520"],"playProbabirity":1000,"playCondType":1,"playCondValues":["3"]},{"stageId":94071401,"sceneType":12,"idx":2,"scriptIds":["9407145530"],"playProbabirity":1000,"playCondType":1,"playCondValues":["2"]},{"stageId":94071401,"sceneType":14,"idx":1,"scriptIds":["9407145610"],"playProbabirity":1000,"playCondType":0,"playCondValues":[]},{"stageId":94071402,"sceneType":1,"idx":1,"scriptIds":["9407145020"],"playProbabirity":1000,"playCondType":0,"playCondValues":[]},{"stageId":94071402,"sceneType":4,"idx":1,"scriptIds":["9407145120"],"playProbabirity":1000,"playCondType":0,"playCondValues":[]},{"stageId":94071402,"sceneType":6,"idx":1,"scriptIds":["9407145210"],"playProbabirity":1000,"playCondType":0,"playCondValues":[]},{"stageId":94071402,"sceneType":6,"idx":2,"scriptIds":["9407145220"],"playProbabirity":1000,"playCondType":0,"playCondValues":[]},{"stageId":94071402,"sceneType":6,"idx":3,"scriptIds":["9407145230"],"playProbabirity":1000,"playCondType":0,"playCondValues":[]},{"stageId":94071402,"sceneType":8,"idx":1,"scriptIds":["9407145320"],"playProbabirity":1000,"playCondType":0,"playCondValues":[]},{"stageId":94071402,"sceneType":9,"idx":1,"scriptIds":["9407145410"],"playProbabirity":1000,"playCondType":5,"playCondValues":["3"]},{"stageId":94071402,"sceneType":9,"idx":2,"scriptIds":["9407145420"],"playProbabirity":1000,"playCondType":5,"playCondValues":["3"]},{"stageId":94071402,"sceneType":9,"idx":3,"scriptIds":["9407145430"],"playProbabirity":1000,"playCondType":5,"playCondValues":["3"]},{"stageId":94071402,"sceneType":11,"idx":1,"scriptIds":["9407145510"],"playProbabirity":1000,"playCondType":1,"playCondValues":["1"]},{"stageId":94071402,"sceneType":12,"idx":1,"scriptIds":["9407145520"],"playProbabirity":1000,"playCondType":1,"playCondValues":["3"]},{"stageId":94071402,"sceneType":12,"idx":2,"scriptIds":["9407145530"],"playProbabirity":1000,"playCondType":1,"playCondValues":["2"]},{"stageId":94071402,"sceneType":14,"idx":1,"scriptIds":["9407145610"],"playProbabirity":1000,"playCondType":0,"playCondValues":[]},{"stageId":94071403,"sceneType":1,"idx":1,"scriptIds":["9407145030"],"playProbabirity":1000,"playCondType":0,"playCondValues":[]},{"stageId":94071403,"sceneType":4,"idx":1,"scriptIds":["9407145130"],"playProbabirity":1000,"playCondType":0,"playCondValues":[]},{"stageId":94071403,"sceneType":6,"idx":1,"scriptIds":["9407145210"],"playProbabirity":1000,"playCondType":0,"playCondValues":[]},{"stageId":94071403,"sceneType":6,"idx":2,"scriptIds":["9407145220"],"playProbabirity":1000,"playCondType":0,"playCondValues":[]},{"stageId":94071403,"sceneType":6,"idx":3,"scriptIds":["9407145230"],"playProbabirity":1000,"playCondType":0,"playCondValues":[]},{"stageId":94071403,"sceneType":8,"idx":1,"scriptIds":["9407145330"],"playProbabirity":1000,"playCondType":0,"playCondValues":[]},{"stageId":94071403,"sceneType":9,"idx":1,"scriptIds":["9407145410"],"playProbabirity":1000,"playCondType":5,"playCondValues":["3"]},{"stageId":94071403,"sceneType":9,"idx":2,"scriptIds":["9407145420"],"playProbabirity":1000,"playCondType":5,"playCondValues":["3"]},{"stageId":94071403,"sceneType":9,"idx":3,"scriptIds":["9407145430"],"playProbabirity":1000,"playCondType":5,"playCondValues":["3"]},{"stageId":94071403,"sceneType":11,"idx":1,"scriptIds":["9407145510"],"playProbabirity":1000,"playCondType":1,"playCondValues":["1"]},{"stageId":94071403,"sceneType":12,"idx":1,"scriptIds":["9407145520"],"playProbabirity":1000,"playCondType":1,"playCondValues":["3"]},{"stageId":94071403,"sceneType":12,"idx":2,"scriptIds":["9407145530"],"playProbabirity":1000,"playCondType":1,"playCondValues":["2"]},{"stageId":94071403,"sceneType":14,"idx":1,"scriptIds":["9407145610"],"playProbabirity":1000,"playCondType":0,"playCondValues":[]},{"stageId":94071404,"sceneType":1,"idx":1,"scriptIds":["9407145040"],"playProbabirity":1000,"playCondType":0,"playCondValues":[]},{"stageId":94071404,"sceneType":4,"idx":1,"scriptIds":["9407145140"],"playProbabirity":1000,"playCondType":0,"playCondValues":[]},{"stageId":94071404,"sceneType":6,"idx":1,"scriptIds":["9407145240"],"playProbabirity":1000,"playCondType":0,"playCondValues":[]},{"stageId":94071404,"sceneType":6,"idx":2,"scriptIds":["9407145250"],"playProbabirity":1000,"playCondType":0,"playCondValues":[]},{"stageId":94071404,"sceneType":6,"idx":3,"scriptIds":["9407145260"],"playProbabirity":1000,"playCondType":0,"playCondValues":[]},{"stageId":94071404,"sceneType":8,"idx":1,"scriptIds":["9407145340"],"playProbabirity":1000,"playCondType":0,"playCondValues":[]},{"stageId":94071404,"sceneType":9,"idx":1,"scriptIds":["9407145470"],"playProbabirity":1000,"playCondType":4,"playCondValues":["1"]},{"stageId":94071404,"sceneType":10,"idx":1,"scriptIds":["9407145440"],"playProbabirity":1000,"playCondType":4,"playCondValues":["3"]},{"stageId":94071404,"sceneType":10,"idx":2,"scriptIds":["9407145450"],"playProbabirity":1000,"playCondType":4,"playCondValues":["3"]},{"stageId":94071404,"sceneType":10,"idx":3,"scriptIds":["9407145460"],"playProbabirity":1000,"playCondType":4,"playCondValues":["2"]},{"stageId":94071404,"sceneType":11,"idx":1,"scriptIds":["9407145540"],"playProbabirity":1000,"playCondType":1,"playCondValues":["3"]},{"stageId":94071404,"sceneType":12,"idx":1,"scriptIds":["9407145550"],"playProbabirity":1000,"playCondType":1,"playCondValues":["2"]},{"stageId":94071404,"sceneType":12,"idx":2,"scriptIds":["9407145560"],"playProbabirity":1000,"playCondType":1,"playCondValues":["1"]},{"stageId":94071404,"sceneType":14,"idx":1,"scriptIds":["9407145620"],"playProbabirity":1000,"playCondType":0,"playCondValues":[]},{"stageId":94071405,"sceneType":1,"idx":1,"scriptIds":["9407145050"],"playProbabirity":1000,"playCondType":0,"playCondValues":[]},{"stageId":94071405,"sceneType":4,"idx":1,"scriptIds":["9407145150"],"playProbabirity":1000,"playCondType":0,"playCondValues":[]},{"stageId":94071405,"sceneType":6,"idx":1,"scriptIds":["9407145240"],"playProbabirity":1000,"playCondType":0,"playCondValues":[]},{"stageId":94071405,"sceneType":6,"idx":2,"scriptIds":["9407145250"],"playProbabirity":1000,"playCondType":0,"playCondValues":[]},{"stageId":94071405,"sceneType":6,"idx":3,"scriptIds":["9407145260"],"playProbabirity":1000,"playCondType":0,"playCondValues":[]},{"stageId":94071405,"sceneType":8,"idx":1,"scriptIds":["9407145350"],"playProbabirity":1000,"playCondType":0,"playCondValues":[]},{"stageId":94071405,"sceneType":9,"idx":1,"scriptIds":["9407145470"],"playProbabirity":1000,"playCondType":4,"playCondValues":["1"]},{"stageId":94071405,"sceneType":10,"idx":1,"scriptIds":["9407145440"],"playProbabirity":1000,"playCondType":4,"playCondValues":["3"]},{"stageId":94071405,"sceneType":10,"idx":2,"scriptIds":["9407145450"],"playProbabirity":1000,"playCondType":4,"playCondValues":["3"]},{"stageId":94071405,"sceneType":10,"idx":3,"scriptIds":["9407145460"],"playProbabirity":1000,"playCondType":4,"playCondValues":["2"]},{"stageId":94071405,"sceneType":11,"idx":1,"scriptIds":["9407145540"],"playProbabirity":1000,"playCondType":1,"playCondValues":["3"]},{"stageId":94071405,"sceneType":12,"idx":1,"scriptIds":["9407145550"],"playProbabirity":1000,"playCondType":1,"playCondValues":["2"]},{"stageId":94071405,"sceneType":12,"idx":2,"scriptIds":["9407145560"],"playProbabirity":1000,"playCondType":1,"playCondValues":["1"]},{"stageId":94071405,"sceneType":14,"idx":1,"scriptIds":["9407145620"],"playProbabirity":1000,"playCondType":0,"playCondValues":[]},{"stageId":94071406,"sceneType":1,"idx":1,"scriptIds":["9407145060"],"playProbabirity":1000,"playCondType":0,"playCondValues":[]},{"stageId":94071406,"sceneType":4,"idx":1,"scriptIds":["9407145160"],"playProbabirity":1000,"playCondType":0,"playCondValues":[]},{"stageId":94071406,"sceneType":6,"idx":1,"scriptIds":["9407145240"],"playProbabirity":1000,"playCondType":0,"playCondValues":[]},{"stageId":94071406,"sceneType":6,"idx":2,"scriptIds":["9407145250"],"playProbabirity":1000,"playCondType":0,"playCondValues":[]},{"stageId":94071406,"sceneType":6,"idx":3,"scriptIds":["9407145260"],"playProbabirity":1000,"playCondType":0,"playCondValues":[]},{"stageId":94071406,"sceneType":8,"idx":1,"scriptIds":["9407145360"],"playProbabirity":1000,"playCondType":0,"playCondValues":[]},{"stageId":94071406,"sceneType":9,"idx":1,"scriptIds":["9407145470"],"playProbabirity":1000,"playCondType":4,"playCondValues":["1"]},{"stageId":94071406,"sceneType":10,"idx":1,"scriptIds":["9407145440"],"playProbabirity":1000,"playCondType":4,"playCondValues":["3"]},{"stageId":94071406,"sceneType":10,"idx":2,"scriptIds":["9407145450"],"playProbabirity":1000,"playCondType":4,"playCondValues":["3"]},{"stageId":94071406,"sceneType":10,"idx":3,"scriptIds":["9407145460"],"playProbabirity":1000,"playCondType":4,"playCondValues":["2"]},{"stageId":94071406,"sceneType":11,"idx":1,"scriptIds":["9407145540"],"playProbabirity":1000,"playCondType":1,"playCondValues":["3"]},{"stageId":94071406,"sceneType":12,"idx":1,"scriptIds":["9407145550"],"playProbabirity":1000,"playCondType":1,"playCondValues":["2"]},{"stageId":94071406,"sceneType":12,"idx":2,"scriptIds":["9407145560"],"playProbabirity":1000,"playCondType":1,"playCondValues":["1"]},{"stageId":94071406,"sceneType":14,"idx":1,"scriptIds":["9407145620"],"playProbabirity":1000,"playCondType":0,"playCondValues":[]},{"stageId":94071407,"sceneType":4,"idx":1,"scriptIds":["9407145170"],"playProbabirity":1000,"playCondType":0,"playCondValues":[]},{"stageId":94071407,"sceneType":6,"idx":1,"scriptIds":["9407145710"],"playProbabirity":1000,"playCondType":0,"playCondValues":[]},{"stageId":94071407,"sceneType":6,"idx":2,"scriptIds":["9407145720"],"playProbabirity":1000,"playCondType":0,"playCondValues":[]},{"stageId":94071407,"sceneType":6,"idx":3,"scriptIds":["9407145730"],"playProbabirity":1000,"playCondType":0,"playCondValues":[]},{"stageId":94071407,"sceneType":8,"idx":1,"scriptIds":["9407145770"],"playProbabirity":1000,"playCondType":0,"playCondValues":[]},{"stageId":94071407,"sceneType":9,"idx":1,"scriptIds":["9407145840"],"playProbabirity":1000,"playCondType":4,"playCondValues":["1"]},{"stageId":94071407,"sceneType":10,"idx":1,"scriptIds":["9407145810"],"playProbabirity":1000,"playCondType":4,"playCondValues":["3"]},{"stageId":94071407,"sceneType":10,"idx":2,"scriptIds":["9407145820"],"playProbabirity":1000,"playCondType":4,"playCondValues":["3"]},{"stageId":94071407,"sceneType":10,"idx":3,"scriptIds":["9407145830"],"playProbabirity":1000,"playCondType":4,"playCondValues":["2"]},{"stageId":94071407,"sceneType":11,"idx":1,"scriptIds":["9407145850"],"playProbabirity":1000,"playCondType":1,"playCondValues":["3"]},{"stageId":94071407,"sceneType":12,"idx":1,"scriptIds":["9407145860"],"playProbabirity":1000,"playCondType":1,"playCondValues":["2"]},{"stageId":94071407,"sceneType":12,"idx":2,"scriptIds":["9407145870"],"playProbabirity":1000,"playCondType":1,"playCondValues":["1"]},{"stageId":94071407,"sceneType":14,"idx":1,"scriptIds":["9407145630"],"playProbabirity":1000,"playCondType":0,"playCondValues":[]}]